nones.py
nones-0.0.3.dist-info/METADATA
nones-0.0.3.dist-info/WHEEL
nones-0.0.3.dist-info/top_level.txt
nones-0.0.3.dist-info/RECORD
