Metadata-Version: 2.1
Name: nones
Version: 0.0.3
Summary: Values for using in default arguments.
Home-page: UNKNOWN
Author: Vadim Simakin
Author-email: sima.vad@gmail.com
License: UNKNOWN
Platform: UNKNOWN
Classifier: Programming Language :: Python :: 3
Classifier: Operating System :: OS Independent
Requires-Python: >=3.1
